ipyezannotation/__init__.py
ipyezannotation/annotators/__init__.py
ipyezannotation/annotators/base_annotator.py
ipyezannotation/annotators/image_select_annotator.py
ipyezannotation/studio/__init__.py
ipyezannotation/studio/coders/__init__.py
ipyezannotation/studio/coders/base_coder.py
ipyezannotation/studio/coders/json_coder.py
ipyezannotation/studio/sample.py
ipyezannotation/studio/serializable.py
ipyezannotation/studio/storage/__init__.py
ipyezannotation/studio/storage/base_database.py
ipyezannotation/studio/storage/sqlite/__init__.py
ipyezannotation/studio/storage/sqlite/databases.py
ipyezannotation/studio/storage/sqlite/models.py
ipyezannotation/studio/studio.py
ipyezannotation/studio/widgets/__init__.py
ipyezannotation/studio/widgets/chip.py
ipyezannotation/studio/widgets/navigation_box.py
ipyezannotation/studio/widgets/popup_message.py
ipyezannotation/utils/__init__.py
ipyezannotation/utils/index_counter.py
ipyezannotation/widgets/__init__.py
ipyezannotation/widgets/image_select.py
ipyezannotation/widgets/image_select_gallery.py
ipyezannotation/widgets/multi_progress.py
ipyezannotation/widgets/toggle_button.py
ipyezannotation-0.2.5.dist-info/METADATA
ipyezannotation-0.2.5.dist-info/WHEEL
ipyezannotation-0.2.5.dist-info/RECORD
