Metadata-Version: 2.1
Name: ipyezannotation
Version: 0.2.5
Summary: Easy, simple to customize, pythonic data annotation framework.
Home-page: https://github.com/gMatas/ipyezannotation
Author: Matas Gumbinas
Requires-Python: >=3.8,<4.0
Classifier: Programming Language :: Python :: 3
Classifier: Programming Language :: Python :: 3.8
Classifier: Programming Language :: Python :: 3.9
Classifier: Programming Language :: Python :: 3.10
Classifier: Programming Language :: Python :: 3.11
Requires-Dist: ipython (>=8.7.0,<9.0.0)
Requires-Dist: ipywidgets (>=8.0.3,<9.0.0)
Requires-Dist: sqlmodel (>=0.0.8,<0.0.9)
Project-URL: Repository, https://github.com/gMatas/ipyezannotation
